README.txt
setup.py
cs/__init__.py
cs.plt.contentnegotiator.egg-info/PKG-INFO
cs.plt.contentnegotiator.egg-info/SOURCES.txt
cs.plt.contentnegotiator.egg-info/dependency_links.txt
cs.plt.contentnegotiator.egg-info/entry_points.txt
cs.plt.contentnegotiator.egg-info/namespace_packages.txt
cs.plt.contentnegotiator.egg-info/not-zip-safe
cs.plt.contentnegotiator.egg-info/requires.txt
cs.plt.contentnegotiator.egg-info/top_level.txt
cs/plt/__init__.py
cs/plt/contentnegotiator/__init__.py
cs/plt/contentnegotiator/configure.zcml
cs/plt/contentnegotiator/patches.py
cs/plt/contentnegotiator/version.txt
docs/HISTORY.txt
docs/INSTALL.txt
docs/LICENSE.GPL
docs/LICENSE.txt