Metadata-Version: 1.1
Name: cs.plt.contentnegotiator
Version: 1.3
Summary: A patch to get PloneLanguageTool's contentnegotiator work in virtual hosting environment
Home-page: http://svn.plone.org/svn/plone/plone.app.example
Author: Plone Foundation
Author-email: plone-developers@lists.sourceforge.net
License: GPL
Platform: UNKNOWN
Classifier: Framework :: Plone
Classifier: Programming Language :: Python
Classifier: Topic :: Software Development :: Libraries :: Python Modules
